ei_cli/__init__.py
ei_cli/__main__.py
ei_cli/cli/__init__.py
ei_cli/cli/app.py
ei_cli/cli/commands/image.py
ei_cli/cli/utils.py
ei_cli/config/__init__.py
ei_cli/config/manager.py
ei_cli/config/models.py
ei_cli/core/__init__.py
ei_cli/core/cache.py
ei_cli/core/error_handler.py
ei_cli/core/errors.py
ei_cli/core/models.py
ei_cli/core/progress.py
ei_cli/core/rate_limiter.py
ei_cli/plugins/__init__.py
ei_cli/plugins/base.py
ei_cli/plugins/image.py
ei_cli/plugins/loader.py
ei_cli/plugins/multi_vision.py
ei_cli/plugins/search.py
ei_cli/plugins/setup_youtube.py
ei_cli/plugins/speak.py
ei_cli/plugins/speak_elevenlabs.py
ei_cli/plugins/transcribe.py
ei_cli/plugins/transcribe_video.py
ei_cli/plugins/translate_audio.py
ei_cli/plugins/vision.py
ei_cli/services/__init__.py
ei_cli/services/ai_service.py
ei_cli/services/audio_chunker.py
ei_cli/services/audio_processor.py
ei_cli/services/base.py
ei_cli/services/constants.py
ei_cli/services/elevenlabs_service.py
ei_cli/services/exceptions.py
ei_cli/services/factory.py
ei_cli/services/image_downloader.py
ei_cli/services/image_service.py
ei_cli/services/video_downloader.py
ei_cli/tools/__init__.py
ei_cli/workflow/__init__.py
ei_cli/workflow/interactive.py
ei_cli/workflow/parallel.py
ei_cli/workflow/state.py
everydayai_cli-0.2.2.dist-info/METADATA
everydayai_cli-0.2.2.dist-info/WHEEL
everydayai_cli-0.2.2.dist-info/entry_points.txt
everydayai_cli-0.2.2.dist-info/licenses/LICENSE
everydayai_cli-0.2.2.dist-info/RECORD
