Metadata-Version: 2.4
Name: everydayai-cli
Version: 0.2.2
Summary: EverydayAI CLI - Personal AI toolkit for regular people
License-Expression: MIT
License-File: LICENSE
Keywords: cli,ai,everydayai,productivity,automation
Author: Keith Williams
Author-email: kaw393939@gmail.com
Requires-Python: >=3.11,<4.0
Classifier: Development Status :: 3 - Alpha
Classifier: Intended Audience :: Developers
Classifier: Intended Audience :: Education
Classifier: Topic :: Software Development :: Libraries :: Application Frameworks
Classifier: Programming Language :: Python :: 3
Classifier: Programming Language :: Python :: 3.11
Classifier: Programming Language :: Python :: 3.12
Requires-Dist: aiolimiter (>=1.2.1)
Requires-Dist: backoff (>=2.2.1)
Requires-Dist: click (>=8.1.7)
Requires-Dist: elevenlabs (>=1.0.0)
Requires-Dist: httpx (>=0.28.0)
Requires-Dist: numpy (>=2.3.4)
Requires-Dist: openai (>=2.7.0)
Requires-Dist: pillow (>=12.0.0)
Requires-Dist: pydantic (>=2.5.3)
Requires-Dist: pydantic-settings (>=2.1.0)
Requires-Dist: pyyaml (>=6.0)
Requires-Dist: rich (>=13.7.0)
Requires-Dist: yt-dlp (>=2024.0.0)
Project-URL: Documentation, https://github.com/kaw393939/eai/blob/main/README.md
Project-URL: Homepage, https://keithwilliams.io
Project-URL: Repository, https://github.com/kaw393939/eai
